qsee/__init__.py
qsee/main.py
qsee-2.0.dist-info/LICENSE
qsee-2.0.dist-info/METADATA
qsee-2.0.dist-info/WHEEL
qsee-2.0.dist-info/entry_points.txt
qsee-2.0.dist-info/top_level.txt
qsee-2.0.dist-info/RECORD
