Metadata-Version: 2.1
Name: qsee
Version: 2.0
Summary: qsee: A quantum object search engine
Home-page: https://github.com/vutuanhai237/qsee
Author: Vu Tuan Hai
Author-email: haivt@uit.edu.vn
License: MIT
License-File: LICENSE
Requires-Dist: qiskit
Requires-Dist: qiskit-aer
Requires-Dist: qiskit-ibmq-provider
Requires-Dist: qiskit-ignis
Requires-Dist: qiskit-nature
Requires-Dist: qiskit-terra
Requires-Dist: matplotlib
Requires-Dist: tdqm
Requires-Dist: pytest
